nsc/__init__.py
nsc/__version__.py
nsc/distributions/__init__.py
nsc/distributions/coupled_distribution.py
nsc/distributions/coupled_expotential.py
nsc/distributions/coupled_kullback_leibler.py
nsc/distributions/coupled_normal.py
nsc/distributions/multivariate_coupled_normal.py
nsc/math/__init__.py
nsc/math/entropy.py
nsc/math/entropy_misc.py
nsc/math/entropy_norm.py
nsc/math/function.py
nsc/math/function_old.py
nsc-0.0.4.dist-info/LICENSE
nsc-0.0.4.dist-info/METADATA
nsc-0.0.4.dist-info/WHEEL
nsc-0.0.4.dist-info/top_level.txt
nsc-0.0.4.dist-info/RECORD
