Metadata-Version: 2.1
Name: nsc
Version: 0.0.4
Summary: Library of core functions for the statistics of nonlinear systems.
Home-page: https://github.com/kenricnelson/Nonlinear-Statistical-Coupling.git
Author: Kevin R. Chen, Kenric P. Nelson, John Clements, Daniel Svoboda, and William Thistleton
License: Apache License 2.0
Platform: UNKNOWN
Classifier: Intended Audience :: Science/Research
Classifier: Intended Audience :: Developers
Classifier: Natural Language :: English
Classifier: License :: OSI Approved :: Apache Software License
Classifier: Programming Language :: Python :: 3.6
Classifier: Programming Language :: Python :: 3.7
Classifier: Programming Language :: Python :: 3.8
Classifier: Operating System :: OS Independent
Requires-Python: >= 3.6
Requires-Dist: numpy
Requires-Dist: scipy
